mattermost_api_reference_client/__init__.py
mattermost_api_reference_client/client.py
mattermost_api_reference_client/errors.py
mattermost_api_reference_client/py.typed
mattermost_api_reference_client/types.py
mattermost_api_reference_client/api/__init__.py
mattermost_api_reference_client/api/access_control/__init__.py
mattermost_api_reference_client/api/access_control/assign_access_control_policy_to_channels.py
mattermost_api_reference_client/api/access_control/check_access_control_policy_expression.py
mattermost_api_reference_client/api/access_control/create_access_control_policy.py
mattermost_api_reference_client/api/access_control/delete_access_control_policy.py
mattermost_api_reference_client/api/access_control/get_access_control_policy.py
mattermost_api_reference_client/api/access_control/get_access_control_policy_autocomplete_fields.py
mattermost_api_reference_client/api/access_control/get_cel_visual_ast.py
mattermost_api_reference_client/api/access_control/get_channel_access_control_attributes.py
mattermost_api_reference_client/api/access_control/get_channels_for_access_control_policy.py
mattermost_api_reference_client/api/access_control/search_access_control_policies.py
mattermost_api_reference_client/api/access_control/search_channels_for_access_control_policy.py
mattermost_api_reference_client/api/access_control/test_access_control_policy_expression.py
mattermost_api_reference_client/api/access_control/unassign_access_control_policy_from_channels.py
mattermost_api_reference_client/api/access_control/update_access_control_policy_active_status.py
mattermost_api_reference_client/api/access_control/validate_expression_against_requester.py
mattermost_api_reference_client/api/audit_logs/__init__.py
mattermost_api_reference_client/api/audit_logs/add_audit_log_certificate.py
mattermost_api_reference_client/api/audit_logs/remove_audit_log_certificate.py
mattermost_api_reference_client/api/bleve/__init__.py
mattermost_api_reference_client-4.1.1.post0.dist-info/licenses/LICENSE
mattermost_api_reference_client-4.1.1.post0.dist-info/METADATA
mattermost_api_reference_client-4.1.1.post0.dist-info/WHEEL
mattermost_api_reference_client-4.1.1.post0.dist-info/top_level.txt
mattermost_api_reference_client-4.1.1.post0.dist-info/RECORD
