Metadata-Version: 2.4
Name: mattermost-api-reference-client
Version: 4.1.1.post0
Summary: A client library for accessing Mattermost API
Author-email: Nicolas Cedilnik <nicoco@nicoco.fr>
Project-URL: Repository, https://git.sr.ht/~nicoco/mattermost-api-reference-client
Requires-Python: >=3.9
License-File: LICENSE
Requires-Dist: httpx<0.29.0,>=0.23.0
Requires-Dist: attrs>=22.2.0
Requires-Dist: python-dateutil<3,>=2.8.0
Dynamic: license-file
